pymedx/__init__.py
pymedx/api.py
pymedx/article.py
pymedx/book.py
pymedx/helpers.py
pymedx-0.5.1.dist-info/LICENCE
pymedx-0.5.1.dist-info/METADATA
pymedx-0.5.1.dist-info/WHEEL
pymedx-0.5.1.dist-info/RECORD
