Metadata-Version: 2.3
Name: pymedx
Version: 0.5.1
Summary: PyMedX is a tool set for handling multimedia files.
License: MIT
Author: Gijs Wobben
Author-email: gijswobben@gmail.com
Requires-Python: >3.9,<4
Classifier: License :: OSI Approved :: MIT License
Classifier: Programming Language :: Python :: 3
Classifier: Programming Language :: Python :: 3.10
Classifier: Programming Language :: Python :: 3.11
Classifier: Programming Language :: Python :: 3.12
Classifier: Programming Language :: Python :: 3.13
Requires-Dist: eval-type-backport (>=0.2) ; python_version < "3.10"
Requires-Dist: lxml (>=5.1.0)
Requires-Dist: requests (>=2.20.0)
Requires-Dist: typeguard (>=4)
Requires-Dist: types-lxml (>=2023.10.21)
Requires-Dist: types-requests (>=2.32)
Requires-Dist: typing-extensions (>=4.12)
